<div3 id="elem.10.10" n="10" type="propositions i&#x2014;47">
      <head>PROPOSITION 10.</head>
      <p><hi rend="ital">To find two straight lines incommensurable, the one in length only, and the other in square also, with an assigned straight line</hi>. </p>
      <p>Let <hi rend="ital">A</hi> be the assigned straight line; thus it is required to find two straight lines incommensurable, the one in length only, and the other in square also, with <hi rend="ital">A</hi>. </p>
      <p>Let two numbers <hi rend="ital">B</hi>, <hi rend="ital">C</hi> be set out which have not to one <hi rend="center">as <hi rend="ital">B</hi> is to <hi rend="ital">C</hi>, so is the square on <hi rend="ital">A</hi> to the square on <hi rend="ital">D</hi></hi>
       <ref target="elem.10.6.p.1" targOrder="U">X. 6, Por.</ref>] therefore the square on <hi rend="ital">A</hi> is commensurable with the square on <hi rend="ital">D</hi>. [<ref target="elem.10.6" targOrder="U">X. 6</ref>] </p>
      <p>And, since <hi rend="ital">B</hi> has not to <hi rend="ital">C</hi> the ratio which a square number has to a square number, therefore neither has the square on <hi rend="ital">A</hi> to the square on <hi rend="ital">D</hi> the ratio which a square number has to a square number; therefore <hi rend="ital">A</hi> is incommensurable in length with <hi rend="ital">D</hi>. [<ref target="elem.10.9" targOrder="U">X. 9</ref>] </p>
      <p>Let <hi rend="ital">E</hi> be taken a mean proportional between <hi rend="ital">A</hi>, <hi rend="ital">D</hi>; therefore, as <hi rend="ital">A</hi> is to <hi rend="ital">D</hi>, so is the square on <hi rend="ital">A</hi> to the square on <hi rend="ital">E</hi>. [<ref target="elem.5.def.9" targOrder="U">V. Def. 9</ref>] </p>
      <p>But <hi rend="ital">A</hi> is incommensurable in length with <hi rend="ital">D</hi>; therefore the square on <hi rend="ital">A</hi> is also incommensurable with the square on <hi rend="ital">E</hi>; [<ref target="elem.10.11" targOrder="U">X. 11</ref>] therefore <hi rend="ital">A</hi> is incommensurable in square with <hi rend="ital">E</hi>. </p>
      <p>Therefore two straight lines <hi rend="ital">D</hi>, <hi rend="ital">E</hi> have been found incommensurable, <hi rend="ital">D</hi> in length only, and <hi rend="ital">E</hi> in square and of course in length also, with the assigned straight line <hi rend="ital">A</hi>.]</p>
     </div3>
     
